{
  "id": "backstop_default",
  "viewports": [
    {
      "label": "tablet",
      "width": 1024,
      "height": 768
    }
  ],
  "onBeforeScript": "puppet/onBefore.js",
  "onReadyScript": "puppet/onReady.js",
  "scenarios": [
    {
      "label": "Taylor Swift",
      "url": "http://localhost:8888/w/index.php?title=Taylor_Swift&useparsoid=0",
      "referenceUrl": "http://localhost:8888/w/index.php?title=Taylor_Swift&useparsoid=1",
      "misMatchThreshold" : 0.6,
      "removeSelectors": [  "#toc","#siteNotice" ],
      "delay": 4000,
      "requireSameDimensions": true
    },
    {
      "label": "Hospet",
      "url": "http://localhost:8888/w/index.php?title=Hospet&useparsoid=0&mfproviderproject=wikivoyage",
      "referenceUrl": "http://localhost:8888/w/index.php?title=Hospet&useparsoid=1&mfproviderproject=wikivoyage",
      "misMatchThreshold" : 0.6,
      "removeSelectors": [ "#toc", "#siteNotice", ".listingeditor-add" ],
      "delay": 4000,
      "requireSameDimensions": true
    },

    {
      "label": "Domus_Aurea",
      "url": "http://localhost:8888/w/index.php?title=Domus_Aurea_(vestibolo_e_stagno)&mfproviderlang=it&mfproviderproject=wikipedia&useparsoid=0&",
      "referenceUrl": "http://localhost:8888/w/index.php?title=Domus_Aurea_(vestibolo_e_stagno)&mfproviderlang=it&useparsoid=1&mfproviderproject=wikipedia",
      "misMatchThreshold" : 0.6,
      "removeSelectors": [ "#toc", "#siteNotice", ".hatnote-icon", ".wikitable"  ],
      "delay": 4000,
      "requireSameDimensions": true
    }
  ],
  "paths": {
    "bitmaps_reference": "backstop_data/bitmaps_reference",
    "bitmaps_test": "backstop_data/bitmaps_test",
    "engine_scripts": "backstop_data/engine_scripts",
    "html_report": "backstop_data/html_report",
    "ci_report": "backstop_data/ci_report"
  },
  "report": ["browser"],
  "engine": "puppeteer",
  "engineOptions": {
    "args": ["--no-sandbox"]
  },
  "asyncCaptureLimit": 5,
  "asyncCompareLimit": 50,
  "debug": false,
  "debugWindow": false
}
